__init__.py
quantumlime.py
quantumlime-1.9.0.dist-info/LICENSE
quantumlime-1.9.0.dist-info/METADATA
quantumlime-1.9.0.dist-info/WHEEL
quantumlime-1.9.0.dist-info/top_level.txt
quantumlime-1.9.0.dist-info/RECORD
