Metadata-Version: 2.1
Name: quantumlime
Version: 1.9.0
Summary: QLIME (Quantum Local Interpretable Model-agnostic Explanations) is a Python library for interpreting quantum neural networks using local surrogate models.
Author-email: Quantum Lime <quantumlime@outlook.com>
License: 
Project-URL: Homepage, https://github.com/lirandepira/qlime
Requires-Python: >=3.9
License-File: LICENSE
Requires-Dist: numpy
Requires-Dist: scikit-learn
Requires-Dist: qiskit
Requires-Dist: qiskit-aer
Requires-Dist: matplotlib
